[
  {
    "name": "City Center Badminton Club",
    "description": "120 Members | Weekly Matches",
    "image": "https://via.placeholder.com/250x150.png?text=Badminton+Club"
  },
  {
    "name": "Downtown Soccer League",
    "description": "200 Members | Daily Practices",
    "image": "https://via.placeholder.com/250x150.png?text=Soccer+League"
  },
  {
    "name": "Local Tennis Champs",
    "description": "75 Members | Monthly Tournaments",
    "image": "https://via.placeholder.com/250x150.png?text=Tennis+Champs"
  },
  {
    "name": "Community Cricket Club",
    "description": "150 Members | Weekend Games",
    "image": "https://via.placeholder.com/250x150.png?text=Cricket+Club"
  },
  {
    "name": "Fitness Freaks Jogging Club",
    "description": "60 Members | Morning Sessions",
    "image": "https://via.placeholder.com/250x150.png?text=Jogging+Club"
  },
  {
    "name": "Chess Enthusiasts",
    "description": "50 Members | Weekly Challenges",
    "image": "https://via.placeholder.com/250x150.png?text=Chess+Club"
  },
  {
    "name": "Chess Enthusiasts",
    "description": "50 Members | Weekly Challenges",
    "image": "https://via.placeholder.com/250x150.png?text=Chess+Club"
  },
  {
    "name": "Chess Enthusiasts",
    "description": "50 Members | Weekly Challenges",
    "image": "https://via.placeholder.com/250x150.png?text=Chess+Club"
  },
  {
    "name": "Chess Enthusiasts",
    "description": "50 Members | Weekly Challenges",
    "image": "https://via.placeholder.com/250x150.png?text=Chess+Club"
  },
  {
    "name": "Chess Enthusiasts",
    "description": "50 Members | Weekly Challenges",
    "image": "https://via.placeholder.com/250x150.png?text=Chess+Club"
  },
  {
    "name": "Chess Enthusiasts",
    "description": "50 Members | Weekly Challenges",
    "image": "https://via.placeholder.com/250x150.png?text=Chess+Club"
  },
  {
    "name": "Chess Enthusiasts",
    "description": "50 Members | Weekly Challenges",
    "image": "https://via.placeholder.com/250x150.png?text=Chess+Club"
  },
  {
    "name": "Chess Enthusiasts",
    "description": "50 Members | Weekly Challenges",
    "image": "https://via.placeholder.com/250x150.png?text=Chess+Club"
  },
  {
    "name": "Chess Enthusiasts",
    "description": "50 Members | Weekly Challenges",
    "image": "https://via.placeholder.com/250x150.png?text=Chess+Club"
  },
  {
    "name": "Chess Enthusiasts",
    "description": "50 Members | Weekly Challenges",
    "image": "https://via.placeholder.com/250x150.png?text=Chess+Club"
  },
  {
    "name": "Chess Enthusiasts",
    "description": "50 Members | Weekly Challenges",
    "image": "https://via.placeholder.com/250x150.png?text=Chess+Club"
  }
]
